procmon_parser/__init__.py
procmon_parser/configuration.py
procmon_parser/configuration_format.py
procmon_parser/construct_helper.py
procmon_parser/consts.py
procmon_parser/logs.py
procmon_parser/stream_helper.py
procmon_parser/stream_logs_detail_format.py
procmon_parser/stream_logs_format.py
procmon_parser-0.3.13.dist-info/LICENSE
procmon_parser-0.3.13.dist-info/METADATA
procmon_parser-0.3.13.dist-info/WHEEL
procmon_parser-0.3.13.dist-info/top_level.txt
procmon_parser-0.3.13.dist-info/RECORD
