Metadata-Version: 2.1
Name: procmon-parser
Version: 0.3.13
Summary: Parser to Procmon configuration and log files formats
Home-page: https://github.com/eronnen/procmon-parser.git
Download-URL: https://github.com/eronnen/procmon-parser/archive/v0.3.0.tar.gz
Author: Ely Ronnen
Author-email: elyronnen@gmail.com
Classifier: Intended Audience :: Developers
Classifier: Intended Audience :: Education
Classifier: Programming Language :: Python :: 2.7
Classifier: Programming Language :: Python :: 3.6
Classifier: Programming Language :: Python :: 3.7
Classifier: Programming Language :: Python :: 3.8
Classifier: Programming Language :: Python :: 3.9
Classifier: Programming Language :: Python :: 3.10
Classifier: Programming Language :: Python :: 3.11
Classifier: License :: OSI Approved :: MIT License
Classifier: Operating System :: OS Independent
Requires-Python: >=2.7, !=3.0.*, !=3.1.*, !=3.2.*, !=3.3.*, !=3.4.*, !=3.5.*
License-File: LICENSE
